model_dotenv/__init__.py
model_dotenv/exceptions.py
model_dotenv-0.0.0.1.dist-info/LICENCE
model_dotenv-0.0.0.1.dist-info/METADATA
model_dotenv-0.0.0.1.dist-info/WHEEL
model_dotenv-0.0.0.1.dist-info/top_level.txt
model_dotenv-0.0.0.1.dist-info/RECORD
