Metadata-Version: 2.1
Name: model-dotenv
Version: 0.0.0.1
Summary: A small example package
Home-page: https://github.com/pypa/sampleproject
Author: Example Author
Author-email: author@example.com
License: UNKNOWN
Project-URL: Bug Tracker, https://github.com/pypa/sampleproject/issues
Platform: UNKNOWN
Classifier: Programming Language :: Python :: 3
Classifier: License :: OSI Approved :: MIT License
Classifier: Operating System :: OS Independent
Requires-Python: >=3.6
License-File: LICENCE
Requires-Dist: pydantic
Requires-Dist: python-dotenv
